[
	{
		"idIncidente" : 4
	},
	{
		"idIncidente" : 7
	},
	{
		"idIncidente" : 14
	},
	{
		"idIncidente" : 20
	},
	{
		"idIncidente" : 23
	},
	{
		"idIncidente" : 27
	},
	{
		"idIncidente" : 33
	},
	{
		"idIncidente" : 40
	},
	{
		"idIncidente" : 41
	},
	{
		"idIncidente" : 43
	},
	{
		"idIncidente" : 44
	},
	{
		"idIncidente" : 46
	},
	{
		"idIncidente" : 48
	},
	{
		"idIncidente" : 51
	},
	{
		"idIncidente" : 57
	},
	{
		"idIncidente" : 63
	},
	{
		"idIncidente" : 72
	},
	{
		"idIncidente" : 80
	},
	{
		"idIncidente" : 83
	},
	{
		"idIncidente" : 86
	},
	{
		"idIncidente" : 90
	},
	{
		"idIncidente" : 91
	},
	{
		"idIncidente" : 95
	},
	{
		"idIncidente" : 96
	},
	{
		"idIncidente" : 103
	},
	{
		"idIncidente" : 113
	},
	{
		"idIncidente" : 122
	},
	{
		"idIncidente" : 123
	},
	{
		"idIncidente" : 127
	},
	{
		"idIncidente" : 132
	},
	{
		"idIncidente" : 137
	},
	{
		"idIncidente" : 142
	},
	{
		"idIncidente" : 148
	}
]
